[
  {
    "id": "UG-C",
    "name": "Central",
    "level": 1,
    "level_name": "Region",
    "country": "UG",
    "source": "Wikipedia",
    "source_url": "https://en.wikipedia.org/wiki/Districts_of_Uganda",
    "children": [
      { "name": "Buikwe",      "level": 2, "level_name": "District" },
      { "name": "Bukomansimbi","level": 2, "level_name": "District" },
      { "name": "Butambala",   "level": 2, "level_name": "District" },
      { "name": "Buvuma",      "level": 2, "level_name": "District" },
      { "name": "Gomba",       "level": 2, "level_name": "District" },
      { "name": "Kalangala",   "level": 2, "level_name": "District" },
      { "name": "Kalungu",     "level": 2, "level_name": "District" },
      { "name": "Kampala",     "level": 2, "level_name": "District" },
      { "name": "Kassanda",    "level": 2, "level_name": "District" },
      { "name": "Kayunga",     "level": 2, "level_name": "District" },
      { "name": "Kiboga",      "level": 2, "level_name": "District" },
      { "name": "Kyankwanzi",  "level": 2, "level_name": "District" },
      { "name": "Kyotera",     "level": 2, "level_name": "District" },
      { "name": "Luweero",     "level": 2, "level_name": "District" },
      { "name": "Lwengo",      "level": 2, "level_name": "District" },
      { "name": "Lyantonde",   "level": 2, "level_name": "District" },
      { "name": "Masaka",      "level": 2, "level_name": "District" },
      { "name": "Mityana",     "level": 2, "level_name": "District" },
      { "name": "Mpigi",       "level": 2, "level_name": "District" },
      { "name": "Mubende",     "level": 2, "level_name": "District" },
      { "name": "Mukono",      "level": 2, "level_name": "District" },
      { "name": "Nakaseke",    "level": 2, "level_name": "District" },
      { "name": "Nakasongola", "level": 2, "level_name": "District" },
      { "name": "Rakai",       "level": 2, "level_name": "District" },
      { "name": "Sembabule",   "level": 2, "level_name": "District" },
      { "name": "Wakiso",      "level": 2, "level_name": "District" }
    ]
  },
  {
    "id": "UG-E",
    "name": "Eastern",
    "level": 1,
    "level_name": "Region",
    "country": "UG",
    "source": "Wikipedia",
    "source_url": "https://en.wikipedia.org/wiki/Districts_of_Uganda",
    "children": [
      { "name": "Amuria",      "level": 2, "level_name": "District" },
      { "name": "Budaka",      "level": 2, "level_name": "District" },
      { "name": "Bududa",      "level": 2, "level_name": "District" },
      { "name": "Bugiri",      "level": 2, "level_name": "District" },
      { "name": "Bugweri",     "level": 2, "level_name": "District" },
      { "name": "Bukedea",     "level": 2, "level_name": "District" },
      { "name": "Bukwo",       "level": 2, "level_name": "District" },
      { "name": "Bulambuli",   "level": 2, "level_name": "District" },
      { "name": "Busia",       "level": 2, "level_name": "District" },
      { "name": "Butaleja",    "level": 2, "level_name": "District" },
      { "name": "Butebo",      "level": 2, "level_name": "District" },
      { "name": "Buyende",     "level": 2, "level_name": "District" },
      { "name": "Iganga",      "level": 2, "level_name": "District" },
      { "name": "Jinja",       "level": 2, "level_name": "District" },
      { "name": "Kaberamaido", "level": 2, "level_name": "District" },
      { "name": "Kalaki",      "level": 2, "level_name": "District" },
      { "name": "Kaliro",      "level": 2, "level_name": "District" },
      { "name": "Kamuli",      "level": 2, "level_name": "District" },
      { "name": "Kapchorwa",   "level": 2, "level_name": "District" },
      { "name": "Kapelebyong", "level": 2, "level_name": "District" },
      { "name": "Katakwi",     "level": 2, "level_name": "District" },
      { "name": "Kibuku",      "level": 2, "level_name": "District" },
      { "name": "Kumi",        "level": 2, "level_name": "District" },
      { "name": "Kween",       "level": 2, "level_name": "District" },
      { "name": "Luuka",       "level": 2, "level_name": "District" },
      { "name": "Manafwa",     "level": 2, "level_name": "District" },
      { "name": "Mayuge",      "level": 2, "level_name": "District" },
      { "name": "Mbale",       "level": 2, "level_name": "District" },
      { "name": "Namayingo",   "level": 2, "level_name": "District" },
      { "name": "Namisindwa",  "level": 2, "level_name": "District" },
      { "name": "Namutumba",   "level": 2, "level_name": "District" },
      { "name": "Ngora",       "level": 2, "level_name": "District" },
      { "name": "Pallisa",     "level": 2, "level_name": "District" },
      { "name": "Serere",      "level": 2, "level_name": "District" },
      { "name": "Sironko",     "level": 2, "level_name": "District" },
      { "name": "Soroti",      "level": 2, "level_name": "District" },
      { "name": "Tororo",      "level": 2, "level_name": "District" }
    ]
  },
  {
    "id": "UG-N",
    "name": "Northern",
    "level": 1,
    "level_name": "Region",
    "country": "UG",
    "source": "Wikipedia",
    "source_url": "https://en.wikipedia.org/wiki/Districts_of_Uganda",
    "children": [
      { "name": "Abim",           "level": 2, "level_name": "District" },
      { "name": "Adjumani",       "level": 2, "level_name": "District" },
      { "name": "Agago",          "level": 2, "level_name": "District" },
      { "name": "Alebtong",       "level": 2, "level_name": "District" },
      { "name": "Amolatar",       "level": 2, "level_name": "District" },
      { "name": "Amudat",         "level": 2, "level_name": "District" },
      { "name": "Amuru",          "level": 2, "level_name": "District" },
      { "name": "Apac",           "level": 2, "level_name": "District" },
      { "name": "Arua",           "level": 2, "level_name": "District" },
      { "name": "Dokolo",         "level": 2, "level_name": "District" },
      { "name": "Gulu",           "level": 2, "level_name": "District" },
      { "name": "Kaabong",        "level": 2, "level_name": "District" },
      { "name": "Karenga",        "level": 2, "level_name": "District" },
      { "name": "Kitgum",         "level": 2, "level_name": "District" },
      { "name": "Koboko",         "level": 2, "level_name": "District" },
      { "name": "Kole",           "level": 2, "level_name": "District" },
      { "name": "Kotido",         "level": 2, "level_name": "District" },
      { "name": "Kwania",         "level": 2, "level_name": "District" },
      { "name": "Lamwo",          "level": 2, "level_name": "District" },
      { "name": "Lira",           "level": 2, "level_name": "District" },
      { "name": "Madi-Okollo",    "level": 2, "level_name": "District" },
      { "name": "Maracha",        "level": 2, "level_name": "District" },
      { "name": "Moroto",         "level": 2, "level_name": "District" },
      { "name": "Moyo",           "level": 2, "level_name": "District" },
      { "name": "Nabilatuk",      "level": 2, "level_name": "District" },
      { "name": "Nakapiripirit",  "level": 2, "level_name": "District" },
      { "name": "Napak",          "level": 2, "level_name": "District" },
      { "name": "Nebbi",          "level": 2, "level_name": "District" },
      { "name": "Nwoya",          "level": 2, "level_name": "District" },
      { "name": "Obongi",         "level": 2, "level_name": "District" },
      { "name": "Omoro",          "level": 2, "level_name": "District" },
      { "name": "Otuke",          "level": 2, "level_name": "District" },
      { "name": "Oyam",           "level": 2, "level_name": "District" },
      { "name": "Pader",          "level": 2, "level_name": "District" },
      { "name": "Pakwach",        "level": 2, "level_name": "District" },
      { "name": "Terego",         "level": 2, "level_name": "District" },
      { "name": "Yumbe",          "level": 2, "level_name": "District" },
      { "name": "Zombo",          "level": 2, "level_name": "District" }
    ]
  },
  {
    "id": "UG-W",
    "name": "Western",
    "level": 1,
    "level_name": "Region",
    "country": "UG",
    "source": "Wikipedia",
    "source_url": "https://en.wikipedia.org/wiki/Districts_of_Uganda",
    "children": [
      { "name": "Buhweju",     "level": 2, "level_name": "District" },
      { "name": "Buliisa",     "level": 2, "level_name": "District" },
      { "name": "Bundibugyo",  "level": 2, "level_name": "District" },
      { "name": "Bunyangabu",  "level": 2, "level_name": "District" },
      { "name": "Bushenyi",    "level": 2, "level_name": "District" },
      { "name": "Hoima",       "level": 2, "level_name": "District" },
      { "name": "Ibanda",      "level": 2, "level_name": "District" },
      { "name": "Isingiro",    "level": 2, "level_name": "District" },
      { "name": "Kabale",      "level": 2, "level_name": "District" },
      { "name": "Kabarole",    "level": 2, "level_name": "District" },
      { "name": "Kagadi",      "level": 2, "level_name": "District" },
      { "name": "Kakumiro",    "level": 2, "level_name": "District" },
      { "name": "Kamwenge",    "level": 2, "level_name": "District" },
      { "name": "Kanungu",     "level": 2, "level_name": "District" },
      { "name": "Kasese",      "level": 2, "level_name": "District" },
      { "name": "Kazo",        "level": 2, "level_name": "District" },
      { "name": "Kibaale",     "level": 2, "level_name": "District" },
      { "name": "Kikuube",     "level": 2, "level_name": "District" },
      { "name": "Kiruhura",    "level": 2, "level_name": "District" },
      { "name": "Kiryandongo", "level": 2, "level_name": "District" },
      { "name": "Kisoro",      "level": 2, "level_name": "District" },
      { "name": "Kitagwenda",  "level": 2, "level_name": "District" },
      { "name": "Kyegegwa",    "level": 2, "level_name": "District" },
      { "name": "Kyenjojo",    "level": 2, "level_name": "District" },
      { "name": "Masindi",     "level": 2, "level_name": "District" },
      { "name": "Mbarara",     "level": 2, "level_name": "District" },
      { "name": "Mitooma",     "level": 2, "level_name": "District" },
      { "name": "Ntoroko",     "level": 2, "level_name": "District" },
      { "name": "Ntungamo",    "level": 2, "level_name": "District" },
      { "name": "Rubanda",     "level": 2, "level_name": "District" },
      { "name": "Rubirizi",    "level": 2, "level_name": "District" },
      { "name": "Rukiga",      "level": 2, "level_name": "District" },
      { "name": "Rukungiri",   "level": 2, "level_name": "District" },
      { "name": "Rwampara",    "level": 2, "level_name": "District" },
      { "name": "Sheema",      "level": 2, "level_name": "District" }
    ]
  }
]
